{"version": 0.6, "generator": "Overpass API 0.7.62.11 87bfad18", "osm3s": {"timestamp_osm_base": "2026-04-09T10:51:45Z", "copyright": "The data included in this document is from www.openstreetmap.org. The data is made available under ODbL."}, "elements": [{"type": "node", "id": 6467321044, "lat": -5.6026257, "lon": -44.62064}, {"type": "node", "id": 6467321045, "lat": -5.6029357, "lon": -44.6203498}, {"type": "node", "id": 6467321046, "lat": -5.6036261, "lon": -44.619819}, {"type": "node", "id": 6467321047, "lat": -5.6040135, "lon": -44.6196278}, {"type": "node", "id": 6467321048, "lat": -5.604408, "lon": -44.6195075}, {"type": "node", "id": 6467321049, "lat": -5.6046334, "lon": -44.6193518}, {"type": "node", "id": 6467321050, "lat": -5.6048941, "lon": -44.6189908}, {"type": "node", "id": 6467321051, "lat": -5.6049786, "lon": -44.6186793}, {"type": "node", "id": 6467321052, "lat": -5.6049786, "lon": -44.6183679}, {"type": "node", "id": 6467321053, "lat": -5.6049857, "lon": -44.6178512}, {"type": "node", "id": 6467321054, "lat": -5.6051195, "lon": -44.6174972}, {"type": "node", "id": 6467321055, "lat": -5.6052393, "lon": -44.6171646}, {"type": "node", "id": 6467321056, "lat": -5.6057183, "lon": -44.6166195}, {"type": "node", "id": 6467321057, "lat": -5.6058662, "lon": -44.6164355}, {"type": "node", "id": 6467321058, "lat": -5.606155, "lon": -44.6161382}, {"type": "node", "id": 6467321059, "lat": -5.6063241, "lon": -44.6159258}, {"type": "node", "id": 6467321060, "lat": -5.6064932, "lon": -44.6154162}, {"type": "node", "id": 6467321061, "lat": -5.6066693, "lon": -44.6147721}, {"type": "node", "id": 6467321062, "lat": -5.6069511, "lon": -44.6146305}, {"type": "node", "id": 6467321063, "lat": -5.6073526, "lon": -44.6138589}, {"type": "node", "id": 6467321064, "lat": -5.6074583, "lon": -44.6135263}, {"type": "node", "id": 6467321065, "lat": -5.6075992, "lon": -44.6131582}, {"type": "node", "id": 6467321066, "lat": -5.6077964, "lon": -44.6129883}, {"type": "node", "id": 6467321067, "lat": -5.60805, "lon": -44.6129104}, {"type": "node", "id": 6467321068, "lat": -5.6082825, "lon": -44.6129671}, {"type": "node", "id": 6467321069, "lat": -5.6084586, "lon": -44.6129812}, {"type": "node", "id": 6467321070, "lat": -5.6088108, "lon": -44.6129104}, {"type": "node", "id": 6467321071, "lat": -5.6091631, "lon": -44.6127547}, {"type": "node", "id": 6467321072, "lat": -5.609466, "lon": -44.6125636}, {"type": "node", "id": 6467321073, "lat": -5.609628, "lon": -44.6119832}, {"type": "node", "id": 6467321074, "lat": -5.609635, "lon": -44.6114948}, {"type": "node", "id": 6467321075, "lat": -5.609635, "lon": -44.6111196}, {"type": "node", "id": 6467321076, "lat": -5.6096984, "lon": -44.6108577}, {"type": "node", "id": 6467321077, "lat": -5.6097689, "lon": -44.6106737}, {"type": "node", "id": 6467321078, "lat": -5.6104311, "lon": -44.6099163}, {"type": "node", "id": 6467321079, "lat": -5.6109453, "lon": -44.6094562}, {"type": "node", "id": 6467321080, "lat": -5.6111707, "lon": -44.6092792}, {"type": "node", "id": 6467321081, "lat": -5.611375, "lon": -44.6091801}, {"type": "node", "id": 6467321082, "lat": -5.6116709, "lon": -44.6090952}, {"type": "node", "id": 6467321083, "lat": -5.6124176, "lon": -44.6089961}, {"type": "node", "id": 6467321084, "lat": -5.6129389, "lon": -44.6087979}, {"type": "node", "id": 6467321285, "lat": -5.6136715, "lon": -44.6085502}, {"type": "node", "id": 6467321286, "lat": -5.6144323, "lon": -44.6082245}, {"type": "node", "id": 6467321287, "lat": -5.6147352, "lon": -44.6080688}, {"type": "node", "id": 6467321288, "lat": -5.6151086, "lon": -44.6079626}, {"type": "node", "id": 6467321289, "lat": -5.6153974, "lon": -44.6078919}, {"type": "node", "id": 6467321290, "lat": -5.6156369, "lon": -44.6078423}, {"type": "node", "id": 6467321291, "lat": -5.6162216, "lon": -44.6075804}, {"type": "node", "id": 6467321292, "lat": -5.6166372, "lon": -44.607269}, {"type": "node", "id": 6467321293, "lat": -5.6171233, "lon": -44.6068726}, {"type": "node", "id": 6467321294, "lat": -5.6175389, "lon": -44.6067027}, {"type": "node", "id": 6467321295, "lat": -5.6178066, "lon": -44.6065682}, {"type": "node", "id": 6467321296, "lat": -5.6181025, "lon": -44.6063771}, {"type": "node", "id": 6467321297, "lat": -5.6183913, "lon": -44.6063134}, {"type": "node", "id": 6467321298, "lat": -5.6191309, "lon": -44.6062143}, {"type": "node", "id": 6467321299, "lat": -5.6193845, "lon": -44.6061931}, {"type": "node", "id": 6467321300, "lat": -5.6196663, "lon": -44.6061931}, {"type": "node", "id": 6467321301, "lat": -5.6200467, "lon": -44.6058816}, {"type": "node", "id": 6467321302, "lat": -5.6202439, "lon": -44.605825}, {"type": "node", "id": 6467321303, "lat": -5.6208145, "lon": -44.6054215}, {"type": "node", "id": 6467321304, "lat": -5.6211386, "lon": -44.6051738}, {"type": "node", "id": 6467321305, "lat": -5.6213992, "lon": -44.6049826}, {"type": "node", "id": 6467321306, "lat": -5.6216387, "lon": -44.6048057}, {"type": "node", "id": 6467321307, "lat": -5.6222164, "lon": -44.6046146}, {"type": "node", "id": 6467321308, "lat": -5.6225193, "lon": -44.6046146}, {"type": "node", "id": 6467321309, "lat": -5.6234209, "lon": -44.604289}, {"type": "node", "id": 6467321310, "lat": -5.6236534, "lon": -44.6041686}, {"type": "node", "id": 6467321311, "lat": -5.6238647, "lon": -44.6041616}, {"type": "node", "id": 6467321312, "lat": -5.6241817, "lon": -44.6041616}, {"type": "node", "id": 6467321313, "lat": -5.6245973, "lon": -44.6040766}, {"type": "node", "id": 6467321314, "lat": -5.6249848, "lon": -44.6039775}, {"type": "node", "id": 6467321315, "lat": -5.6256258, "lon": -44.6037015}, {"type": "node", "id": 6467321316, "lat": -5.6260626, "lon": -44.6034325}, {"type": "node", "id": 6467321317, "lat": -5.6266895, "lon": -44.6032697}, {"type": "node", "id": 6467321318, "lat": -5.6276827, "lon": -44.6029653}, {"type": "node", "id": 6467321319, "lat": -5.6282322, "lon": -44.6028096}, {"type": "node", "id": 6467321320, "lat": -5.6286337, "lon": -44.6026397}, {"type": "node", "id": 6467321321, "lat": -5.6291339, "lon": -44.6023141}, {"type": "node", "id": 6467321322, "lat": -5.6294438, "lon": -44.602123}, {"type": "node", "id": 6467321323, "lat": -5.6298312, "lon": -44.6019035}, {"type": "node", "id": 6467321324, "lat": -5.6302046, "lon": -44.6017054}, {"type": "node", "id": 6467321325, "lat": -5.6310569, "lon": -44.6015638}, {"type": "node", "id": 6467321326, "lat": -5.6313105, "lon": -44.6014222}, {"type": "node", "id": 6467321327, "lat": -5.6315994, "lon": -44.6012453}, {"type": "node", "id": 6467321328, "lat": -5.6319163, "lon": -44.60104}, {"type": "node", "id": 6467321329, "lat": -5.6323672, "lon": -44.6007144}, {"type": "node", "id": 6467321330, "lat": -5.6330012, "lon": -44.6002472}, {"type": "node", "id": 6467321331, "lat": -5.6338535, "lon": -44.5997022}, {"type": "node", "id": 6467321332, "lat": -5.6340226, "lon": -44.5995323}, {"type": "node", "id": 6467321333, "lat": -5.6344875, "lon": -44.5992491}, {"type": "node", "id": 6467321334, "lat": -5.6348749, "lon": -44.5990934}, {"type": "node", "id": 6467321335, "lat": -5.6352342, "lon": -44.599058}, {"type": "node", "id": 6467321336, "lat": -5.6355441, "lon": -44.5991076}, {"type": "node", "id": 6467321337, "lat": -5.636319, "lon": -44.5992138}, {"type": "node", "id": 6467321338, "lat": -5.6367416, "lon": -44.599235}, {"type": "node", "id": 6467321339, "lat": -5.6372347, "lon": -44.5992421}, {"type": "node", "id": 6467321340, "lat": -5.6378264, "lon": -44.5991996}, {"type": "node", "id": 6467321341, "lat": -5.6386083, "lon": -44.5991501}, {"type": "node", "id": 6467321342, "lat": -5.638876, "lon": -44.5991784}, {"type": "node", "id": 6467321343, "lat": -5.6392071, "lon": -44.5992279}, {"type": "node", "id": 6467321344, "lat": -5.6401439, "lon": -44.5992208}, {"type": "node", "id": 6467321345, "lat": -5.6405595, "lon": -44.5991217}, {"type": "node", "id": 6467321346, "lat": -5.6409822, "lon": -44.5990651}, {"type": "node", "id": 6467321347, "lat": -5.6412076, "lon": -44.599058}, {"type": "node", "id": 6467321348, "lat": -5.6415105, "lon": -44.5990297}, {"type": "node", "id": 6467321349, "lat": -5.6418697, "lon": -44.5990651}, {"type": "node", "id": 6467321350, "lat": -5.6424685, "lon": -44.5991217}, {"type": "node", "id": 6467321351, "lat": -5.6428559, "lon": -44.5991925}, {"type": "node", "id": 6467321352, "lat": -5.6438773, "lon": -44.5996385}, {"type": "node", "id": 6467321353, "lat": -5.6442013, "lon": -44.5997446}, {"type": "node", "id": 6467321354, "lat": -5.6447719, "lon": -44.5999782}, {"type": "node", "id": 6467321355, "lat": -5.6452579, "lon": -44.6001552}, {"type": "node", "id": 6467321356, "lat": -5.6457722, "lon": -44.6002684}, {"type": "node", "id": 6467321357, "lat": -5.6463639, "lon": -44.6003251}, {"type": "node", "id": 6467321358, "lat": -5.6466668, "lon": -44.6002614}, {"type": "node", "id": 6467321359, "lat": -5.6471176, "lon": -44.600141}, {"type": "node", "id": 6467321360, "lat": -5.6475402, "lon": -44.6001269}, {"type": "node", "id": 6467321361, "lat": -5.6479488, "lon": -44.5999995}, {"type": "node", "id": 6467321362, "lat": -5.6490829, "lon": -44.5996668}, {"type": "node", "id": 6467321363, "lat": -5.6497591, "lon": -44.5994757}, {"type": "node", "id": 6467321364, "lat": -5.6502099, "lon": -44.5992987}, {"type": "node", "id": 6467321365, "lat": -5.6515835, "lon": -44.5988528}, {"type": "node", "id": 6467321366, "lat": -5.6522738, "lon": -44.5986333}, {"type": "node", "id": 6467321367, "lat": -5.6019584, "lon": -44.62144}, {"type": "node", "id": 6467321368, "lat": -5.6017448, "lon": -44.6219657}, {"type": "node", "id": 6467321369, "lat": -5.6014032, "lon": -44.6222768}, {"type": "node", "id": 6467321370, "lat": -5.6009654, "lon": -44.6224378}, {"type": "node", "id": 6467321371, "lat": -5.6003995, "lon": -44.6226309}, {"type": "node", "id": 6467321372, "lat": -5.5998229, "lon": -44.6229528}, {"type": "node", "id": 6467321373, "lat": -5.5990648, "lon": -44.6236823}, {"type": "node", "id": 6467321374, "lat": -5.5988085, "lon": -44.6239935}, {"type": "node", "id": 6467321375, "lat": -5.5985736, "lon": -44.6242402}, {"type": "node", "id": 6467321376, "lat": -5.5980183, "lon": -44.6249054}, {"type": "node", "id": 6467321377, "lat": -5.5975912, "lon": -44.6250342}, {"type": "node", "id": 6467321378, "lat": -5.5972602, "lon": -44.6251522}, {"type": "node", "id": 6467321379, "lat": -5.5965662, "lon": -44.6259354}, {"type": "node", "id": 6467321380, "lat": -5.5963847, "lon": -44.6262143}, {"type": "node", "id": 6467321381, "lat": -5.5959789, "lon": -44.6265576}, {"type": "node", "id": 6467321382, "lat": -5.5954023, "lon": -44.6267293}, {"type": "node", "id": 6467321383, "lat": -5.5946655, "lon": -44.6269332}, {"type": "node", "id": 6467321384, "lat": -5.5943452, "lon": -44.6270512}, {"type": "node", "id": 6467321485, "lat": -5.5939395, "lon": -44.6273516}, {"type": "node", "id": 6467321486, "lat": -5.5937259, "lon": -44.6278988}, {"type": "node", "id": 6467321487, "lat": -5.5937793, "lon": -44.6284888}, {"type": "node", "id": 6467321488, "lat": -5.5938861, "lon": -44.6289502}, {"type": "node", "id": 6467321489, "lat": -5.593854, "lon": -44.6291648}, {"type": "node", "id": 6467321490, "lat": -5.5935337, "lon": -44.6294974}, {"type": "node", "id": 6467321491, "lat": -5.593128, "lon": -44.6298085}, {"type": "node", "id": 6467321492, "lat": -5.5927222, "lon": -44.6301304}, {"type": "node", "id": 6467321493, "lat": -5.5924339, "lon": -44.6303557}, {"type": "node", "id": 6467321494, "lat": -5.5920175, "lon": -44.6308063}, {"type": "node", "id": 6467321495, "lat": -5.5908643, "lon": -44.6311818}, {"type": "node", "id": 6467321496, "lat": -5.5907682, "lon": -44.6312247}, {"type": "node", "id": 6467321497, "lat": -5.5902236, "lon": -44.6314071}, {"type": "node", "id": 6467321498, "lat": -5.589679, "lon": -44.6318577}, {"type": "node", "id": 6467321499, "lat": -5.5895295, "lon": -44.6324263}, {"type": "node", "id": 6467321500, "lat": -5.5895402, "lon": -44.6328447}, {"type": "node", "id": 6467321501, "lat": -5.5893694, "lon": -44.6331022}, {"type": "node", "id": 6467321502, "lat": -5.5891772, "lon": -44.6336387}, {"type": "node", "id": 6467321503, "lat": -5.5889636, "lon": -44.633864}, {"type": "node", "id": 6467321504, "lat": -5.5882482, "lon": -44.6343361}, {"type": "node", "id": 6467321505, "lat": -5.5875862, "lon": -44.6342395}, {"type": "node", "id": 6467321506, "lat": -5.5871591, "lon": -44.6337567}, {"type": "node", "id": 6467321507, "lat": -5.5863369, "lon": -44.6331022}, {"type": "node", "id": 6467321508, "lat": -5.5859311, "lon": -44.6331988}, {"type": "node", "id": 6467321509, "lat": -5.5853759, "lon": -44.6335636}, {"type": "node", "id": 6467321510, "lat": -5.5849914, "lon": -44.6341751}, {"type": "node", "id": 6467321511, "lat": -5.5848099, "lon": -44.6345828}, {"type": "node", "id": 6467321512, "lat": -5.5843508, "lon": -44.6353875}, {"type": "node", "id": 6467321513, "lat": -5.5839877, "lon": -44.6355913}, {"type": "node", "id": 6467321514, "lat": -5.5837208, "lon": -44.635881}, {"type": "node", "id": 6467321515, "lat": -5.5835392, "lon": -44.6364389}, {"type": "node", "id": 6467321516, "lat": -5.5833577, "lon": -44.6370719}, {"type": "node", "id": 6467321517, "lat": -5.583315, "lon": -44.637383}, {"type": "node", "id": 6467321518, "lat": -5.5831335, "lon": -44.6379946}, {"type": "node", "id": 6467321519, "lat": -5.5827918, "lon": -44.6383379}, {"type": "node", "id": 6467321520, "lat": -5.5824394, "lon": -44.6385632}, {"type": "node", "id": 6467321521, "lat": -5.5818735, "lon": -44.6387134}, {"type": "node", "id": 6467321522, "lat": -5.5812435, "lon": -44.6390889}, {"type": "node", "id": 6467321523, "lat": -5.5808484, "lon": -44.6396576}, {"type": "node", "id": 6467321524, "lat": -5.5805815, "lon": -44.6403335}, {"type": "node", "id": 6467321525, "lat": -5.5804533, "lon": -44.6407197}, {"type": "node", "id": 6467321526, "lat": -5.5802718, "lon": -44.6411596}, {"type": "node", "id": 6467321527, "lat": -5.5798447, "lon": -44.6417175}, {"type": "node", "id": 6467321528, "lat": -5.5792467, "lon": -44.6419428}, {"type": "node", "id": 6467321529, "lat": -5.5784245, "lon": -44.6424149}, {"type": "node", "id": 6467321530, "lat": -5.5781255, "lon": -44.6431873}, {"type": "node", "id": 6467321531, "lat": -5.5779867, "lon": -44.6437345}, {"type": "node", "id": 6467321532, "lat": -5.5778799, "lon": -44.6441315}, {"type": "node", "id": 6467321533, "lat": -5.5777304, "lon": -44.6444533}, {"type": "node", "id": 6467321534, "lat": -5.5773353, "lon": -44.6447323}, {"type": "node", "id": 6467321535, "lat": -5.5768014, "lon": -44.6450971}, {"type": "node", "id": 6467321536, "lat": -5.5763743, "lon": -44.6453224}, {"type": "node", "id": 6467321537, "lat": -5.5761287, "lon": -44.6454833}, {"type": "node", "id": 6467321538, "lat": -5.5756055, "lon": -44.6459983}, {"type": "node", "id": 6467321539, "lat": -5.5752852, "lon": -44.6464489}, {"type": "node", "id": 6467321540, "lat": -5.5749435, "lon": -44.646803}, {"type": "node", "id": 6467321541, "lat": -5.5746872, "lon": -44.6471248}, {"type": "node", "id": 6467321542, "lat": -5.5746018, "lon": -44.6478115}, {"type": "node", "id": 6467321543, "lat": -5.5750396, "lon": -44.6484552}, {"type": "node", "id": 6467321544, "lat": -5.5752745, "lon": -44.6486376}, {"type": "node", "id": 6467321545, "lat": -5.5753279, "lon": -44.6489058}, {"type": "node", "id": 6467321546, "lat": -5.5752852, "lon": -44.649217}, {"type": "node", "id": 6467321547, "lat": -5.5749755, "lon": -44.6495174}, {"type": "node", "id": 6467321548, "lat": -5.5740572, "lon": -44.6495603}, {"type": "node", "id": 6467321549, "lat": -5.5737048, "lon": -44.6496676}, {"type": "node", "id": 6467321550, "lat": -5.573267, "lon": -44.6499787}, {"type": "node", "id": 6467321551, "lat": -5.5731068, "lon": -44.6501933}, {"type": "node", "id": 6467321552, "lat": -5.5726263, "lon": -44.6504293}, {"type": "node", "id": 6467321553, "lat": -5.5720283, "lon": -44.6503435}, {"type": "node", "id": 6467321554, "lat": -5.5716759, "lon": -44.6505366}, {"type": "node", "id": 6467321555, "lat": -5.5713556, "lon": -44.6508048}, {"type": "node", "id": 6467321556, "lat": -5.5709392, "lon": -44.6513949}, {"type": "node", "id": 6467321557, "lat": -5.5707042, "lon": -44.6523712}, {"type": "node", "id": 6467321558, "lat": -5.570811, "lon": -44.6529935}, {"type": "node", "id": 6467321559, "lat": -5.5712275, "lon": -44.6538304}, {"type": "node", "id": 6467321560, "lat": -5.5713022, "lon": -44.6542273}, {"type": "node", "id": 6467321561, "lat": -5.5711848, "lon": -44.6547316}, {"type": "node", "id": 6467321562, "lat": -5.5708964, "lon": -44.6552466}, {"type": "node", "id": 6467321563, "lat": -5.5707363, "lon": -44.6557294}, {"type": "node", "id": 6467321564, "lat": -5.5706295, "lon": -44.6560727}, {"type": "node", "id": 6467321565, "lat": -5.5704586, "lon": -44.6567486}, {"type": "node", "id": 6467321566, "lat": -5.5705013, "lon": -44.657049}, {"type": "node", "id": 6467321567, "lat": -5.5707363, "lon": -44.657682}, {"type": "node", "id": 6467321568, "lat": -5.570779, "lon": -44.658079}, {"type": "node", "id": 6467321569, "lat": -5.5707256, "lon": -44.6584116}, {"type": "node", "id": 6467321570, "lat": -5.5709498, "lon": -44.6590446}, {"type": "node", "id": 6467321571, "lat": -5.5710353, "lon": -44.6595166}, {"type": "node", "id": 6467321572, "lat": -5.5710886, "lon": -44.6599887}, {"type": "node", "id": 6467321573, "lat": -5.571078, "lon": -44.6604179}, {"type": "node", "id": 6467321574, "lat": -5.5712168, "lon": -44.6608041}, {"type": "node", "id": 6467321575, "lat": -5.5712702, "lon": -44.6609758}, {"type": "node", "id": 6467321576, "lat": -5.5713876, "lon": -44.6614371}, {"type": "node", "id": 6467321577, "lat": -5.5714624, "lon": -44.6619199}, {"type": "node", "id": 6467321578, "lat": -5.5715905, "lon": -44.6621452}, {"type": "node", "id": 6467321579, "lat": -5.5715798, "lon": -44.6625851}, {"type": "node", "id": 6467321580, "lat": -5.5715371, "lon": -44.6629284}, {"type": "node", "id": 6467321581, "lat": -5.5715478, "lon": -44.6632825}, {"type": "node", "id": 6467321582, "lat": -5.5715798, "lon": -44.6636043}, {"type": "node", "id": 6467321583, "lat": -5.5715585, "lon": -44.6639691}, {"type": "node", "id": 6467321584, "lat": -5.5713236, "lon": -44.6644412}, {"type": "node", "id": 6467321585, "lat": -5.5709071, "lon": -44.6652995}, {"type": "node", "id": 6467321586, "lat": -5.5705334, "lon": -44.6659217}, {"type": "node", "id": 6467321587, "lat": -5.5703625, "lon": -44.6662651}, {"type": "node", "id": 6467321588, "lat": -5.5702878, "lon": -44.6666299}, {"type": "node", "id": 6467321589, "lat": -5.5704693, "lon": -44.6671341}, {"type": "node", "id": 6467321590, "lat": -5.5706615, "lon": -44.6676491}, {"type": "node", "id": 6467321591, "lat": -5.5706508, "lon": -44.6682606}, {"type": "node", "id": 6467321592, "lat": -5.5705975, "lon": -44.6690868}, {"type": "node", "id": 6467321593, "lat": -5.5705654, "lon": -44.6697841}, {"type": "node", "id": 6467321594, "lat": -5.5704693, "lon": -44.6702026}, {"type": "node", "id": 6467321595, "lat": -5.5701703, "lon": -44.6705995}, {"type": "node", "id": 6467321596, "lat": -5.5696898, "lon": -44.6711145}, {"type": "node", "id": 6467321597, "lat": -5.5693801, "lon": -44.6715758}, {"type": "node", "id": 6467321598, "lat": -5.5691986, "lon": -44.6720157}, {"type": "node", "id": 6467321599, "lat": -5.5690918, "lon": -44.672874}, {"type": "node", "id": 6467321600, "lat": -5.5690918, "lon": -44.6735607}, {"type": "node", "id": 6467321601, "lat": -5.5691666, "lon": -44.6740113}, {"type": "node", "id": 6467321602, "lat": -5.5691239, "lon": -44.6749232}, {"type": "node", "id": 6467321603, "lat": -5.5690918, "lon": -44.675449}, {"type": "node", "id": 6467321604, "lat": -5.5691345, "lon": -44.6758245}, {"type": "node", "id": 6467321605, "lat": -5.5691345, "lon": -44.6763824}, {"type": "node", "id": 6467321606, "lat": -5.5691773, "lon": -44.6769725}, {"type": "node", "id": 6467321607, "lat": -5.5693695, "lon": -44.6773158}, {"type": "node", "id": 6467321608, "lat": -5.5696471, "lon": -44.6774123}, {"type": "node", "id": 6467321609, "lat": -5.5700422, "lon": -44.6774445}, {"type": "node", "id": 6467321610, "lat": -5.57048, "lon": -44.6774552}, {"type": "node", "id": 6467321611, "lat": -5.5705441, "lon": -44.677702}, {"type": "node", "id": 6467321612, "lat": -5.5703839, "lon": -44.677981}, {"type": "node", "id": 6467321613, "lat": -5.5701276, "lon": -44.6780453}, {"type": "node", "id": 6467321614, "lat": -5.5698713, "lon": -44.6780453}, {"type": "node", "id": 6467321615, "lat": -5.5690384, "lon": -44.6783887}, {"type": "node", "id": 6467321616, "lat": -5.5686006, "lon": -44.6792255}, {"type": "node", "id": 6467321617, "lat": -5.5683871, "lon": -44.6797405}, {"type": "node", "id": 6467321618, "lat": -5.5677357, "lon": -44.6810387}, {"type": "node", "id": 6467321619, "lat": -5.5675648, "lon": -44.6816395}, {"type": "node", "id": 6467321620, "lat": -5.5676076, "lon": -44.6823369}, {"type": "node", "id": 6467321621, "lat": -5.5676396, "lon": -44.6830772}, {"type": "node", "id": 6467321622, "lat": -5.567693, "lon": -44.6835814}, {"type": "node", "id": 6467321623, "lat": -5.5677357, "lon": -44.6841286}, {"type": "node", "id": 6467321624, "lat": -5.5679599, "lon": -44.6846865}, {"type": "node", "id": 6467321625, "lat": -5.5682055, "lon": -44.6853088}, {"type": "node", "id": 6467321626, "lat": -5.5681521, "lon": -44.6859847}, {"type": "node", "id": 6467321627, "lat": -5.5678638, "lon": -44.6868001}, {"type": "node", "id": 6467321628, "lat": -5.5672445, "lon": -44.6877549}, {"type": "node", "id": 6467321629, "lat": -5.5669028, "lon": -44.6886883}, {"type": "node", "id": 6467321630, "lat": -5.566764, "lon": -44.6893321}, {"type": "node", "id": 6467321631, "lat": -5.5664009, "lon": -44.6898149}, {"type": "node", "id": 6467321632, "lat": -5.5658029, "lon": -44.6900831}, {"type": "node", "id": 6467321633, "lat": -5.5651302, "lon": -44.6900831}, {"type": "node", "id": 6467321634, "lat": -5.5633042, "lon": -44.6904693}, {"type": "node", "id": 6467321635, "lat": -5.5630052, "lon": -44.690523}, {"type": "node", "id": 6467321636, "lat": -5.5626101, "lon": -44.6909843}, {"type": "node", "id": 6467321637, "lat": -5.562482, "lon": -44.6911345}, {"type": "node", "id": 6467321638, "lat": -5.5620976, "lon": -44.6914671}, {"type": "node", "id": 6467321639, "lat": -5.5619694, "lon": -44.6920357}, {"type": "node", "id": 6467321640, "lat": -5.561916, "lon": -44.692658}, {"type": "node", "id": 6467321641, "lat": -5.561852, "lon": -44.6932266}, {"type": "node", "id": 6467321642, "lat": -5.5618626, "lon": -44.6938275}, {"type": "node", "id": 6467321643, "lat": -5.5618626, "lon": -44.6942459}, {"type": "node", "id": 6467321644, "lat": -5.5611045, "lon": -44.6951149}, {"type": "node", "id": 6467321645, "lat": -5.5604424, "lon": -44.6956835}, {"type": "node", "id": 6467321646, "lat": -5.560058, "lon": -44.6958767}, {"type": "node", "id": 6467321647, "lat": -5.5596309, "lon": -44.696059}, {"type": "node", "id": 6467321648, "lat": -5.5592571, "lon": -44.6965097}, {"type": "node", "id": 6467321649, "lat": -5.5588407, "lon": -44.6971641}, {"type": "node", "id": 6467321650, "lat": -5.5587552, "lon": -44.6973894}, {"type": "node", "id": 6467321651, "lat": -5.5586591, "lon": -44.6981726}, {"type": "node", "id": 6467321652, "lat": -5.5589047, "lon": -44.6989773}, {"type": "node", "id": 6467321653, "lat": -5.558862, "lon": -44.6998571}, {"type": "node", "id": 6467321654, "lat": -5.558798, "lon": -44.7000073}, {"type": "node", "id": 6467321655, "lat": -5.5583708, "lon": -44.7009729}, {"type": "node", "id": 6467321656, "lat": -5.558232, "lon": -44.7013484}, {"type": "node", "id": 6467321657, "lat": -5.5581573, "lon": -44.702035}, {"type": "node", "id": 6467321658, "lat": -5.5579864, "lon": -44.7027324}, {"type": "node", "id": 6467321659, "lat": -5.5576767, "lon": -44.7032474}, {"type": "node", "id": 6467321660, "lat": -5.5572816, "lon": -44.7041593}, {"type": "node", "id": 6467321661, "lat": -5.5570147, "lon": -44.7046958}, {"type": "node", "id": 6467321662, "lat": -5.5568758, "lon": -44.7050176}, {"type": "node", "id": 6467321663, "lat": -5.5566089, "lon": -44.7059618}, {"type": "node", "id": 6467321664, "lat": -5.5566089, "lon": -44.7062514}, {"type": "node", "id": 6467321665, "lat": -5.5565982, "lon": -44.7071098}, {"type": "node", "id": 6467321666, "lat": -5.556737, "lon": -44.7078071}, {"type": "node", "id": 6467321667, "lat": -5.5570253, "lon": -44.708526}, {"type": "node", "id": 6467321668, "lat": -5.5571321, "lon": -44.709159}, {"type": "node", "id": 6467321669, "lat": -5.557634, "lon": -44.7101889}, {"type": "node", "id": 6467321670, "lat": -5.5579864, "lon": -44.7108005}, {"type": "node", "id": 6467321671, "lat": -5.5583922, "lon": -44.711809}, {"type": "node", "id": 6467321672, "lat": -5.5585737, "lon": -44.712324}, {"type": "node", "id": 6467321673, "lat": -5.5587232, "lon": -44.7128282}, {"type": "node", "id": 6467321674, "lat": -5.5590542, "lon": -44.7136222}, {"type": "node", "id": 6467321675, "lat": -5.5594387, "lon": -44.7145019}, {"type": "node", "id": 6467321676, "lat": -5.5598017, "lon": -44.7150491}, {"type": "node", "id": 6467321677, "lat": -5.5602182, "lon": -44.7156499}, {"type": "node", "id": 6467321678, "lat": -5.560688, "lon": -44.7159396}, {"type": "node", "id": 6467321679, "lat": -5.5609443, "lon": -44.7162078}, {"type": "node", "id": 6467321680, "lat": -5.5610725, "lon": -44.7168408}, {"type": "node", "id": 6467321681, "lat": -5.5609657, "lon": -44.717506}, {"type": "node", "id": 6467321682, "lat": -5.5610938, "lon": -44.7183214}, {"type": "node", "id": 6467321683, "lat": -5.5611899, "lon": -44.7188256}, {"type": "node", "id": 6467321684, "lat": -5.5614248, "lon": -44.7190724}, {"type": "node", "id": 6467321685, "lat": -5.5618733, "lon": -44.7196196}, {"type": "node", "id": 6467321686, "lat": -5.5623966, "lon": -44.7199093}, {"type": "node", "id": 6467321687, "lat": -5.5630052, "lon": -44.7204242}, {"type": "node", "id": 6467321688, "lat": -5.5637634, "lon": -44.7213898}, {"type": "node", "id": 6467321689, "lat": -5.5640303, "lon": -44.7219048}, {"type": "node", "id": 6467321690, "lat": -5.5644148, "lon": -44.7223876}, {"type": "node", "id": 6467321691, "lat": -5.5648846, "lon": -44.722967}, {"type": "node", "id": 6467321692, "lat": -5.5650875, "lon": -44.7236}, {"type": "node", "id": 6467321693, "lat": -5.5651088, "lon": -44.7240935}, {"type": "node", "id": 6467321694, "lat": -5.5650661, "lon": -44.7244154}, {"type": "node", "id": 6467321695, "lat": -5.564906, "lon": -44.7247801}, {"type": "node", "id": 6467321696, "lat": -5.5644254, "lon": -44.7249733}, {"type": "node", "id": 6467321697, "lat": -5.5636993, "lon": -44.7252415}, {"type": "node", "id": 6467321698, "lat": -5.5631547, "lon": -44.7254346}, {"type": "node", "id": 6467321699, "lat": -5.5620869, "lon": -44.7258638}, {"type": "node", "id": 6467321700, "lat": -5.5616384, "lon": -44.7261105}, {"type": "node", "id": 6467321701, "lat": -5.560955, "lon": -44.7264431}, {"type": "node", "id": 6467321702, "lat": -5.5605385, "lon": -44.7266577}, {"type": "node", "id": 6467321703, "lat": -5.560325, "lon": -44.7267542}, {"type": "node", "id": 6467321704, "lat": -5.5599512, "lon": -44.7270332}, {"type": "node", "id": 6467321705, "lat": -5.5596416, "lon": -44.7273443}, {"type": "node", "id": 6467321706, "lat": -5.5593212, "lon": -44.7276018}, {"type": "node", "id": 6467321707, "lat": -5.5590329, "lon": -44.727913}, {"type": "node", "id": 6467321708, "lat": -5.5587339, "lon": -44.728031}, {"type": "node", "id": 6467321709, "lat": -5.5578262, "lon": -44.728546}, {"type": "node", "id": 6467321710, "lat": -5.5574418, "lon": -44.7288035}, {"type": "node", "id": 6467321711, "lat": -5.5568331, "lon": -44.7289429}, {"type": "node", "id": 6467321712, "lat": -5.5563419, "lon": -44.729018}, {"type": "node", "id": 6467321713, "lat": -5.5560216, "lon": -44.7290502}, {"type": "node", "id": 6467321714, "lat": -5.5557866, "lon": -44.7290502}, {"type": "node", "id": 6467321715, "lat": -5.5554663, "lon": -44.7290395}, {"type": "node", "id": 6467321716, "lat": -5.5540674, "lon": -44.729415}, {"type": "node", "id": 6467321717, "lat": -5.5537364, "lon": -44.7298227}, {"type": "node", "id": 6467321718, "lat": -5.5534694, "lon": -44.7302948}, {"type": "node", "id": 6467321719, "lat": -5.5530636, "lon": -44.7311102}, {"type": "node", "id": 6467321720, "lat": -5.5528287, "lon": -44.7314213}, {"type": "node", "id": 6467321721, "lat": -5.5526258, "lon": -44.7317968}, {"type": "node", "id": 6467321722, "lat": -5.5523802, "lon": -44.7322152}, {"type": "node", "id": 6467321723, "lat": -5.5522521, "lon": -44.7326337}, {"type": "node", "id": 6467321724, "lat": -5.5520171, "lon": -44.7333203}, {"type": "node", "id": 6467321725, "lat": -5.5517182, "lon": -44.7340391}, {"type": "node", "id": 6467321726, "lat": -5.5515153, "lon": -44.7343395}, {"type": "node", "id": 6467321727, "lat": -5.5509813, "lon": -44.7346399}, {"type": "node", "id": 6467321728, "lat": -5.550725, "lon": -44.7346399}, {"type": "node", "id": 6467321729, "lat": -5.5502552, "lon": -44.7345541}, {"type": "node", "id": 6467321730, "lat": -5.5496145, "lon": -44.7344146}, {"type": "node", "id": 7084800290, "lat": -5.7229478, "lon": -44.7325722}, {"type": "node", "id": 7084800291, "lat": -5.723206, "lon": -44.7322554}, {"type": "node", "id": 7084800292, "lat": -5.7224205, "lon": -44.7321608}, {"type": "node", "id": 7084800293, "lat": -5.7224629, "lon": -44.7322794}, {"type": "node", "id": 7084800294, "lat": -5.7228105, "lon": -44.7318097}, {"type": "node", "id": 7084800295, "lat": -5.7224126, "lon": -44.7316128}, {"type": "node", "id": 7084800296, "lat": -5.7221971, "lon": -44.7317923}, {"type": "node", "id": 7084800297, "lat": -5.7222661, "lon": -44.7316747}, {"type": "node", "id": 7084800298, "lat": -5.7228344, "lon": -44.7323647}, {"type": "node", "id": 7084800299, "lat": -5.722739, "lon": -44.7323777}, {"type": "node", "id": 7084800300, "lat": -5.7228432, "lon": -44.7324963}, {"type": "node", "id": 7084800301, "lat": -5.7228831, "lon": -44.7324509}, {"type": "node", "id": 7084800302, "lat": -5.7221669, "lon": -44.7318535}, {"type": "node", "id": 7084800303, "lat": -5.722373, "lon": -44.731972}, {"type": "node", "id": 7084800304, "lat": -5.7215501, "lon": -44.7313102}, {"type": "node", "id": 7084800305, "lat": -5.7217917, "lon": -44.7309563}, {"type": "node", "id": 7084800306, "lat": -5.7218452, "lon": -44.7309896}, {"type": "node", "id": 7084800307, "lat": -5.7218618, "lon": -44.7310842}, {"type": "node", "id": 7084800308, "lat": -5.7218378, "lon": -44.7311861}, {"type": "node", "id": 7084800309, "lat": -5.7217825, "lon": -44.7312621}, {"type": "node", "id": 7084800310, "lat": -5.721812, "lon": -44.7312917}, {"type": "node", "id": 7084800311, "lat": -5.7218064, "lon": -44.731338}, {"type": "node", "id": 7084800312, "lat": -5.7218064, "lon": -44.7313714}, {"type": "node", "id": 7084800313, "lat": -5.721965, "lon": -44.7314585}, {"type": "node", "id": 7084800314, "lat": -5.7219263, "lon": -44.7315085}, {"type": "node", "id": 7084800315, "lat": -5.7218599, "lon": -44.7315085}, {"type": "node", "id": 7084800316, "lat": -5.7218027, "lon": -44.7315289}, {"type": "node", "id": 7084800317, "lat": -5.7217198, "lon": -44.7315345}, {"type": "node", "id": 7084800318, "lat": -5.7216589, "lon": -44.7315345}, {"type": "node", "id": 7084800319, "lat": -5.7215852, "lon": -44.7315197}, {"type": "node", "id": 7084800320, "lat": -5.7215409, "lon": -44.7314881}, {"type": "node", "id": 7084800321, "lat": -5.7215096, "lon": -44.7314418}, {"type": "node", "id": 7084800322, "lat": -5.7215003, "lon": -44.7314029}, {"type": "node", "id": 7084800356, "lat": -5.695083, "lon": -44.7114759}, {"type": "node", "id": 7084800357, "lat": -5.695182, "lon": -44.7113598}, {"type": "node", "id": 7084800358, "lat": -5.6951985, "lon": -44.7111301}, {"type": "node", "id": 7084800359, "lat": -5.6951419, "lon": -44.7109169}, {"type": "node", "id": 7084800360, "lat": -5.6952008, "lon": -44.7108103}, {"type": "node", "id": 7084800361, "lat": -5.6952055, "lon": -44.7106468}, {"type": "node", "id": 7084800362, "lat": -5.6952079, "lon": -44.7104502}, {"type": "node", "id": 7084800363, "lat": -5.6953022, "lon": -44.7103389}, {"type": "node", "id": 7084800364, "lat": -5.694601, "lon": -44.7089764}, {"type": "node", "id": 7084800365, "lat": -5.6956645, "lon": -44.7095681}, {"type": "node", "id": 7084800366, "lat": -5.6955337, "lon": -44.7099574}, {"type": "node", "id": 7084800381, "lat": -5.7033554, "lon": -44.7107631}, {"type": "node", "id": 7084800382, "lat": -5.7031229, "lon": -44.7106502}, {"type": "node", "id": 7084800383, "lat": -5.7031578, "lon": -44.7105645}, {"type": "node", "id": 7084800384, "lat": -5.7031655, "lon": -44.7104126}, {"type": "node", "id": 7084800385, "lat": -5.7031345, "lon": -44.7103153}, {"type": "node", "id": 7084800386, "lat": -5.703057, "lon": -44.7101751}, {"type": "node", "id": 7084800387, "lat": -5.7030222, "lon": -44.7100777}, {"type": "node", "id": 7084800388, "lat": -5.7032856, "lon": -44.7100388}, {"type": "node", "id": 7084800389, "lat": -5.7034135, "lon": -44.7100622}, {"type": "node", "id": 7084800390, "lat": -5.7035375, "lon": -44.7100855}, {"type": "node", "id": 7084800391, "lat": -5.7035375, "lon": -44.7101985}, {"type": "node", "id": 7084800392, "lat": -5.7035297, "lon": -44.710288}, {"type": "node", "id": 7084800393, "lat": -5.7036382, "lon": -44.7103698}, {"type": "node", "id": 7084800394, "lat": -5.7036344, "lon": -44.7104749}, {"type": "node", "id": 7084800395, "lat": -5.7037119, "lon": -44.7105217}, {"type": "node", "id": 7084800396, "lat": -5.7038785, "lon": -44.7105411}, {"type": "node", "id": 7084800397, "lat": -5.7040102, "lon": -44.7105801}, {"type": "node", "id": 7084800398, "lat": -5.7040063, "lon": -44.7107241}, {"type": "node", "id": 7084800399, "lat": -5.703987, "lon": -44.710802}, {"type": "node", "id": 7084919580, "lat": -5.4781401, "lon": -44.8976738}, {"type": "node", "id": 7084919581, "lat": -5.4773647, "lon": -44.8965382}, {"type": "node", "id": 7084919582, "lat": -5.4770458, "lon": -44.8957883}, {"type": "node", "id": 7084919583, "lat": -5.4771183, "lon": -44.895104}, {"type": "node", "id": 7084919584, "lat": -5.4771473, "lon": -44.8948055}, {"type": "node", "id": 7084919585, "lat": -5.4775603, "lon": -44.8947691}, {"type": "node", "id": 7084919586, "lat": -5.4779517, "lon": -44.8945871}, {"type": "node", "id": 7084919587, "lat": -5.4781473, "lon": -44.8941504}, {"type": "node", "id": 7084919588, "lat": -5.4781401, "lon": -44.8935097}, {"type": "node", "id": 7084919589, "lat": -5.4785749, "lon": -44.8936189}, {"type": "node", "id": 7084919590, "lat": -5.4788792, "lon": -44.8935825}, {"type": "node", "id": 7084919591, "lat": -5.4787705, "lon": -44.8940848}, {"type": "node", "id": 7084919592, "lat": -5.4785459, "lon": -44.8946963}, {"type": "node", "id": 7084919593, "lat": -5.4789445, "lon": -44.894973}, {"type": "node", "id": 7084919594, "lat": -5.4791256, "lon": -44.8952132}, {"type": "node", "id": 7084919595, "lat": -5.4792923, "lon": -44.8955481}, {"type": "node", "id": 7084919596, "lat": -5.4797851, "lon": -44.8955481}, {"type": "node", "id": 7084919597, "lat": -5.4802271, "lon": -44.8954607}, {"type": "node", "id": 7084919598, "lat": -5.4805242, "lon": -44.8957374}, {"type": "node", "id": 7084919599, "lat": -5.4804518, "lon": -44.8960941}, {"type": "node", "id": 7084919600, "lat": -5.480372, "lon": -44.8965527}, {"type": "node", "id": 7084919601, "lat": -5.4797488, "lon": -44.8970405}, {"type": "node", "id": 7084919602, "lat": -5.4796691, "lon": -44.89747}, {"type": "node", "id": 7084919603, "lat": -5.479401, "lon": -44.8978194}, {"type": "node", "id": 7084919604, "lat": -5.4794481, "lon": -44.8992681}, {"type": "node", "id": 7084919605, "lat": -5.4787905, "lon": -44.8983982}, {"type": "node", "id": 7084919606, "lat": -5.4779118, "lon": -44.897106}, {"type": "node", "id": 7084933922, "lat": -5.5510806, "lon": -44.8358898}, {"type": "node", "id": 7084933923, "lat": -5.5511051, "lon": -44.8356354}, {"type": "node", "id": 7084933924, "lat": -5.5510888, "lon": -44.8353317}, {"type": "node", "id": 7084933925, "lat": -5.551146, "lon": -44.8351675}, {"type": "node", "id": 7084933926, "lat": -5.551195, "lon": -44.8350526}, {"type": "node", "id": 7084933927, "lat": -5.5513992, "lon": -44.8350855}, {"type": "node", "id": 7084933928, "lat": -5.5514891, "lon": -44.8352825}, {"type": "node", "id": 7084933929, "lat": -5.5516933, "lon": -44.8353317}, {"type": "node", "id": 7084933930, "lat": -5.5518893, "lon": -44.8353563}, {"type": "node", "id": 7084933931, "lat": -5.5520527, "lon": -44.835422}, {"type": "node", "id": 7084933932, "lat": -5.5521834, "lon": -44.835422}, {"type": "node", "id": 7084933933, "lat": -5.5523795, "lon": -44.8352414}, {"type": "node", "id": 7084933934, "lat": -5.5525102, "lon": -44.8351429}, {"type": "node", "id": 7084933935, "lat": -5.5525674, "lon": -44.835028}, {"type": "node", "id": 7084933936, "lat": -5.5527552, "lon": -44.8349049}, {"type": "node", "id": 7084933937, "lat": -5.5529595, "lon": -44.834987}, {"type": "node", "id": 7084933938, "lat": -5.553131, "lon": -44.8350937}, {"type": "node", "id": 7084933939, "lat": -5.5533597, "lon": -44.8352168}, {"type": "node", "id": 7084933940, "lat": -5.5536456, "lon": -44.835225}, {"type": "node", "id": 7084933941, "lat": -5.5537927, "lon": -44.8352332}, {"type": "node", "id": 7084933942, "lat": -5.5541276, "lon": -44.8354466}, {"type": "node", "id": 7084933943, "lat": -5.5545116, "lon": -44.8356272}, {"type": "node", "id": 7084933944, "lat": -5.5545279, "lon": -44.8364151}, {"type": "node", "id": 7084933945, "lat": -5.5542828, "lon": -44.8361771}, {"type": "node", "id": 7084933946, "lat": -5.5540704, "lon": -44.8359555}, {"type": "node", "id": 7084933947, "lat": -5.5538254, "lon": -44.8357174}, {"type": "node", "id": 7084933948, "lat": -5.5536211, "lon": -44.8357995}, {"type": "node", "id": 7084933949, "lat": -5.5534414, "lon": -44.8358652}, {"type": "node", "id": 7084933950, "lat": -5.5530902, "lon": -44.8359473}, {"type": "node", "id": 7084933951, "lat": -5.5529186, "lon": -44.8360375}, {"type": "node", "id": 7084933952, "lat": -5.5526082, "lon": -44.8360129}, {"type": "node", "id": 7084933953, "lat": -5.5523305, "lon": -44.8360539}, {"type": "node", "id": 7084933954, "lat": -5.5521752, "lon": -44.8361935}, {"type": "node", "id": 7084933955, "lat": -5.5520282, "lon": -44.8363412}, {"type": "node", "id": 7084933956, "lat": -5.5518076, "lon": -44.8363987}, {"type": "node", "id": 7084933957, "lat": -5.5516851, "lon": -44.8364233}, {"type": "node", "id": 7084933958, "lat": -5.5516034, "lon": -44.8361524}, {"type": "node", "id": 7084933959, "lat": -5.551342, "lon": -44.8361278}, {"type": "node", "id": 7084933960, "lat": -5.551146, "lon": -44.8361032}, {"type": "node", "id": 7084933961, "lat": -5.5553611, "lon": -44.8363494}, {"type": "node", "id": 7084933962, "lat": -5.5555408, "lon": -44.8358488}, {"type": "node", "id": 7084940394, "lat": -5.6176476, "lon": -44.8169711}, {"type": "node", "id": 7084940395, "lat": -5.6179656, "lon": -44.8169993}, {"type": "node", "id": 7084940396, "lat": -5.6179843, "lon": -44.8169194}, {"type": "node", "id": 7084940397, "lat": -5.6180872, "lon": -44.8168725}, {"type": "node", "id": 7084940398, "lat": -5.6181948, "lon": -44.8168067}, {"type": "node", "id": 7084940399, "lat": -5.6182977, "lon": -44.816755}, {"type": "node", "id": 7084940400, "lat": -5.6184239, "lon": -44.8167033}, {"type": "node", "id": 7084940401, "lat": -5.6184193, "lon": -44.8166281}, {"type": "node", "id": 7084940402, "lat": -5.6183725, "lon": -44.8165294}, {"type": "node", "id": 7084940403, "lat": -5.6183117, "lon": -44.8164025}, {"type": "node", "id": 7084940404, "lat": -5.6181995, "lon": -44.8162663}, {"type": "node", "id": 7084940405, "lat": -5.6181433, "lon": -44.8162146}, {"type": "node", "id": 7084940406, "lat": -5.6180685, "lon": -44.8161488}, {"type": "node", "id": 7084940407, "lat": -5.6180077, "lon": -44.8161911}, {"type": "node", "id": 7084940408, "lat": -5.6180451, "lon": -44.8162992}, {"type": "node", "id": 7084940409, "lat": -5.6180311, "lon": -44.8163791}, {"type": "node", "id": 7084940410, "lat": -5.617844, "lon": -44.8166281}, {"type": "node", "id": 7084940411, "lat": -5.6177505, "lon": -44.8168114}, {"type": "node", "id": 7084940412, "lat": -5.6176617, "lon": -44.8168678}, {"type": "node", "id": 7084940413, "lat": -5.6185595, "lon": -44.8196825}, {"type": "node", "id": 7084940414, "lat": -5.6186811, "lon": -44.8196449}, {"type": "node", "id": 7084940415, "lat": -5.6186905, "lon": -44.8195462}, {"type": "node", "id": 7084940416, "lat": -5.6187092, "lon": -44.8193583}, {"type": "node", "id": 7084940417, "lat": -5.6187513, "lon": -44.819269}, {"type": "node", "id": 7084940418, "lat": -5.6186858, "lon": -44.8192079}, {"type": "node", "id": 7084940419, "lat": -5.6185829, "lon": -44.8191515}, {"type": "node", "id": 7084940420, "lat": -5.6185175, "lon": -44.819128}, {"type": "node", "id": 7084940421, "lat": -5.6184613, "lon": -44.8191797}, {"type": "node", "id": 7084940422, "lat": -5.6184193, "lon": -44.8193348}, {"type": "node", "id": 7084940423, "lat": -5.6184005, "lon": -44.8194663}, {"type": "node", "id": 7084940424, "lat": -5.6184052, "lon": -44.819612}, {"type": "node", "id": 7084940425, "lat": -5.6184146, "lon": -44.8196778}, {"type": "way", "id": 689398821, "nodes": [6467321366, 6467321365, 6467321364, 6467321363, 6467321362, 6467321361, 6467321360, 6467321359, 6467321358, 6467321357, 6467321356, 6467321355, 6467321354, 6467321353, 6467321352, 6467321351, 6467321350, 6467321349, 6467321348, 6467321347, 6467321346, 6467321345, 6467321344, 6467321343, 6467321342, 6467321341, 6467321340, 6467321339, 6467321338, 6467321337, 6467321336, 6467321335, 6467321334, 6467321333, 6467321332, 6467321331, 6467321330, 6467321329, 6467321328, 6467321327, 6467321326, 6467321325, 6467321324, 6467321323, 6467321322, 6467321321, 6467321320, 6467321319, 6467321318, 6467321317, 6467321316, 6467321315, 6467321314, 6467321313, 6467321312, 6467321311, 6467321310, 6467321309, 6467321308, 6467321307, 6467321306, 6467321305, 6467321304, 6467321303, 6467321302, 6467321301, 6467321300, 6467321299, 6467321298, 6467321297, 6467321296, 6467321295, 6467321294, 6467321293, 6467321292, 6467321291, 6467321290, 6467321289, 6467321288, 6467321287, 6467321286, 6467321285, 6467321084, 6467321083, 6467321082, 6467321081, 6467321080, 6467321079, 6467321078, 6467321077, 6467321076, 6467321075, 6467321074, 6467321073, 6467321072, 6467321071, 6467321070, 6467321069, 6467321068, 6467321067, 6467321066, 6467321065, 6467321064, 6467321063, 6467321062, 6467321061, 6467321060, 6467321059, 6467321058, 6467321057, 6467321056, 6467321055, 6467321054, 6467321053, 6467321052, 6467321051, 6467321050, 6467321049, 6467321048, 6467321047, 6467321046, 6467321045, 6467321044, 6467321367, 6467321368, 6467321369, 6467321370, 6467321371, 6467321372, 6467321373, 6467321374, 6467321375, 6467321376, 6467321377, 6467321378, 6467321379, 6467321380, 6467321381, 6467321382, 6467321383, 6467321384, 6467321485, 6467321486, 6467321487, 6467321488, 6467321489, 6467321490, 6467321491, 6467321492, 6467321493, 6467321494, 6467321495, 6467321496, 6467321497, 6467321498, 6467321499, 6467321500, 6467321501, 6467321502, 6467321503, 6467321504, 6467321505, 6467321506, 6467321507, 6467321508, 6467321509, 6467321510, 6467321511, 6467321512, 6467321513, 6467321514, 6467321515, 6467321516, 6467321517, 6467321518, 6467321519, 6467321520, 6467321521, 6467321522, 6467321523, 6467321524, 6467321525, 6467321526, 6467321527, 6467321528, 6467321529, 6467321530, 6467321531, 6467321532, 6467321533, 6467321534, 6467321535, 6467321536, 6467321537, 6467321538, 6467321539, 6467321540, 6467321541, 6467321542, 6467321543, 6467321544, 6467321545, 6467321546, 6467321547, 6467321548, 6467321549, 6467321550, 6467321551, 6467321552, 6467321553, 6467321554, 6467321555, 6467321556, 6467321557, 6467321558, 6467321559, 6467321560, 6467321561, 6467321562, 6467321563, 6467321564, 6467321565, 6467321566, 6467321567, 6467321568, 6467321569, 6467321570, 6467321571, 6467321572, 6467321573, 6467321574, 6467321575, 6467321576, 6467321577, 6467321578, 6467321579, 6467321580, 6467321581, 6467321582, 6467321583, 6467321584, 6467321585, 6467321586, 6467321587, 6467321588, 6467321589, 6467321590, 6467321591, 6467321592, 6467321593, 6467321594, 6467321595, 6467321596, 6467321597, 6467321598, 6467321599, 6467321600, 6467321601, 6467321602, 6467321603, 6467321604, 6467321605, 6467321606, 6467321607, 6467321608, 6467321609, 6467321610, 6467321611, 6467321612, 6467321613, 6467321614, 6467321615, 6467321616, 6467321617, 6467321618, 6467321619, 6467321620, 6467321621, 6467321622, 6467321623, 6467321624, 6467321625, 6467321626, 6467321627, 6467321628, 6467321629, 6467321630, 6467321631, 6467321632, 6467321633, 6467321634, 6467321635, 6467321636, 6467321637, 6467321638, 6467321639, 6467321640, 6467321641, 6467321642, 6467321643, 6467321644, 6467321645, 6467321646, 6467321647, 6467321648, 6467321649, 6467321650, 6467321651, 6467321652, 6467321653, 6467321654, 6467321655, 6467321656, 6467321657, 6467321658, 6467321659, 6467321660, 6467321661, 6467321662, 6467321663, 6467321664, 6467321665, 6467321666, 6467321667, 6467321668, 6467321669, 6467321670, 6467321671, 6467321672, 6467321673, 6467321674, 6467321675, 6467321676, 6467321677, 6467321678, 6467321679, 6467321680, 6467321681, 6467321682, 6467321683, 6467321684, 6467321685, 6467321686, 6467321687, 6467321688, 6467321689, 6467321690, 6467321691, 6467321692, 6467321693, 6467321694, 6467321695, 6467321696, 6467321697, 6467321698, 6467321699, 6467321700, 6467321701, 6467321702, 6467321703, 6467321704, 6467321705, 6467321706, 6467321707, 6467321708, 6467321709, 6467321710, 6467321711, 6467321712, 6467321713, 6467321714, 6467321715, 6467321716, 6467321717, 6467321718, 6467321719, 6467321720, 6467321721, 6467321722, 6467321723, 6467321724, 6467321725, 6467321726, 6467321727, 6467321728, 6467321729, 6467321730], "tags": {"waterway": "stream"}}, {"type": "way", "id": 758588600, "nodes": [7084800290, 7084800291, 7084800294, 7084800295, 7084800297, 7084800296, 7084800302, 7084800303, 7084800292, 7084800293, 7084800299, 7084800298, 7084800301, 7084800300, 7084800290], "tags": {"natural": "water"}}, {"type": "way", "id": 758588601, "nodes": [7084800304, 7084800305, 7084800306, 7084800307, 7084800308, 7084800309, 7084800310, 7084800311, 7084800312, 7084800313, 7084800314, 7084800315, 7084800316, 7084800317, 7084800318, 7084800319, 7084800320, 7084800321, 7084800322, 7084800304], "tags": {"intermittent": "yes", "natural": "water"}}, {"type": "way", "id": 758588604, "nodes": [7084800356, 7084800357, 7084800358, 7084800359, 7084800360, 7084800361, 7084800362, 7084800363, 7084800366, 7084800365, 7084800364], "tags": {"waterway": "river"}}, {"type": "way", "id": 758588606, "nodes": [7084800381, 7084800382, 7084800383, 7084800384, 7084800385, 7084800386, 7084800387, 7084800388, 7084800389, 7084800390, 7084800391, 7084800392, 7084800393, 7084800394, 7084800395, 7084800396, 7084800397, 7084800398, 7084800399, 7084800381], "tags": {"natural": "water"}}, {"type": "way", "id": 758599398, "nodes": [7084919580, 7084919606, 7084919581, 7084919582, 7084919583, 7084919584, 7084919585, 7084919586, 7084919587, 7084919588, 7084919589, 7084919590, 7084919591, 7084919592, 7084919593, 7084919594, 7084919595, 7084919596, 7084919597, 7084919598, 7084919599, 7084919600, 7084919601, 7084919602, 7084919603, 7084919604, 7084919605, 7084919580], "tags": {"natural": "water"}}, {"type": "way", "id": 758601132, "nodes": [7084933922, 7084933923, 7084933924, 7084933925, 7084933926, 7084933927, 7084933928, 7084933929, 7084933930, 7084933931, 7084933932, 7084933933, 7084933934, 7084933935, 7084933936, 7084933937, 7084933938, 7084933939, 7084933940, 7084933941, 7084933942, 7084933943, 7084933962, 7084933961, 7084933944, 7084933945, 7084933946, 7084933947, 7084933948, 7084933949, 7084933950, 7084933951, 7084933952, 7084933953, 7084933954, 7084933955, 7084933956, 7084933957, 7084933958, 7084933959, 7084933960, 7084933922], "tags": {"natural": "water"}}, {"type": "way", "id": 758601135, "nodes": [7084940394, 7084940395, 7084940396, 7084940397, 7084940398, 7084940399, 7084940400, 7084940401, 7084940402, 7084940403, 7084940404, 7084940405, 7084940406, 7084940407, 7084940408, 7084940409, 7084940410, 7084940411, 7084940412, 7084940394], "tags": {"natural": "water"}}, {"type": "way", "id": 758601136, "nodes": [7084940413, 7084940414, 7084940415, 7084940416, 7084940417, 7084940418, 7084940419, 7084940420, 7084940421, 7084940422, 7084940423, 7084940424, 7084940425, 7084940413], "tags": {"natural": "water"}}]}